kmeruniq/.build.py.swp
kmeruniq/.query.py.swp
kmeruniq/__init__.py
kmeruniq/__main__.py
kmeruniq/build.py
kmeruniq/cli.py
kmeruniq/index.py
kmeruniq/parsing.py
kmeruniq/query.py
kmeruniq-0.6.dist-info/METADATA
kmeruniq-0.6.dist-info/WHEEL
kmeruniq-0.6.dist-info/entry_points.txt
kmeruniq-0.6.dist-info/RECORD
